fb_api_wrapper/__init__.c
fb_api_wrapper/__init__.cpython-312-x86_64-linux-gnu.so
fb_api_wrapper/__init__.py
fb_api_wrapper/libs/__init__.c
fb_api_wrapper/libs/__init__.cpython-312-x86_64-linux-gnu.so
fb_api_wrapper/libs/__init__.py
fb_api_wrapper/libs/define_api.c
fb_api_wrapper/libs/define_api.cpython-312-x86_64-linux-gnu.so
fb_api_wrapper/libs/define_api.py
fb_api_wrapper/libs/fb_core.c
fb_api_wrapper/libs/fb_core.cpython-312-x86_64-linux-gnu.so
fb_api_wrapper/libs/fb_core.py
fb_api_wrapper/libs/log_.c
fb_api_wrapper/libs/log_.cpython-312-x86_64-linux-gnu.so
fb_api_wrapper/libs/log_.py
fb_api_wrapper/libs/parse_api.c
fb_api_wrapper/libs/parse_api.cpython-312-x86_64-linux-gnu.so
fb_api_wrapper/libs/parse_api.py
fb_api_wrapper/libs/utils.c
fb_api_wrapper/libs/utils.cpython-312-x86_64-linux-gnu.so
fb_api_wrapper/libs/utils.py
fb_api_wrapper-1.1.1.dist-info/METADATA
fb_api_wrapper-1.1.1.dist-info/WHEEL
fb_api_wrapper-1.1.1.dist-info/top_level.txt
fb_api_wrapper-1.1.1.dist-info/RECORD
