Metadata-Version: 2.1
Name: fb_api_wrapper
Version: 1.1.1
Summary: Facebook API wrapper (Cythonized)
